[{"album_group": "album", "album_type": "album", "artists": [{"external_urls": {"spotify": "https://open.spotify.com/artist/0Qbd0AGWuzggX61s306wZN"}, "href": "https://api.spotify.com/v1/artists/0Qbd0AGWuzggX61s306wZN", "id": "0Qbd0AGWuzggX61s306wZN", "name": "Ebru Ya\u015far", "type": "artist", "uri": "spotify:artist:0Qbd0AGWuzggX61s306wZN"}], "available_markets": ["AR", "AU", "AT", "BE", "BO", "BR", "BG", "CA", "CL", "CO", "CR", "CY", "CZ", "DK", "DO", "DE", "EC", "EE", "SV", "FI", "FR", "GR", "GT", "HN", "HK", "HU", "IS", "IE", "IT", "LV", "LT", "LU", "MY", "MT", "MX", "NL", "NZ", "NI", "NO", "PA", "PY", "PE", "PH", "PL", "PT", "SG", "SK", "ES", "SE", "CH", "TW", "TR", "UY", "US", "GB", "AD", "LI", "MC", "ID", "JP", "TH", "VN", "RO", "IL", "ZA", "SA", "AE", "BH", "QA", "OM", "KW", "EG", "MA", "DZ", "TN", "LB", "JO", "PS", "IN", "BY", "KZ", "MD", "UA", "AL", "BA", "HR", "ME", "MK", "RS", "SI", "KR", "BD", "PK", "LK", "GH", "KE", "NG", "TZ", "UG", "AG", "AM", "BS", "BB", "BZ", "BT", "BW", "BF", "CV", "CW", "DM", "FJ", "GM", "GE", "GD", "GW", "GY", "HT", "JM", "KI", "LS", "LR", "MW", "MV", "ML", "MH", "FM", "NA", "NR", "NE", "PW", "PG", "WS", "SM", "ST", "SN", "SC", "SL", "SB", "KN", "LC", "VC", "SR", "TL", "TO", "TT", "TV", "VU", "AZ", "BN", "BI", "KH", "CM", "TD", "KM", "GQ", "SZ", "GA", "GN", "KG", "LA", "MO", "MR", "MN", "NP", "RW", "TG", "UZ", "ZW", "BJ", "MG", "MU", "MZ", "AO", "CI", "DJ", "ZM", "CD", "CG", "IQ", "LY", "TJ", "VE", "ET", "XK"], "external_urls": {"spotify": "https://open.spotify.com/album/1c5POl6xYq8bwrK59Avypj"}, "href": "https://api.spotify.com/v1/albums/1c5POl6xYq8bwrK59Avypj", "id": "1c5POl6xYq8bwrK59Avypj", "images": [{"height": 640, "url": "https://i.scdn.co/image/ab67616d0000b2739d4d02c02df4389dbec39251", "width": 640}, {"height": 300, "url": "https://i.scdn.co/image/ab67616d00001e029d4d02c02df4389dbec39251", "width": 300}, {"height": 64, "url": "https://i.scdn.co/image/ab67616d000048519d4d02c02df4389dbec39251", "width": 64}], "name": "Gel De Sevme", "release_date": "2021-04-09", "release_date_precision": "day", "total_tracks": 10, "type": "album", "uri": "spotify:album:1c5POl6xYq8bwrK59Avypj"}, {"album_group": "album", "album_type": "album", "artists": [{"external_urls": {"spotify": "https://open.spotify.com/artist/0Qbd0AGWuzggX61s306wZN"}, "href": "https://api.spotify.com/v1/artists/0Qbd0AGWuzggX61s306wZN", "id": "0Qbd0AGWuzggX61s306wZN", "name": "Ebru Ya\u015far", "type": "artist", "uri": "spotify:artist:0Qbd0AGWuzggX61s306wZN"}], "available_markets": ["AR", "AU", "AT", "BE", "BO", "BR", "BG", "CA", "CL", "CO", "CR", "CY", "CZ", "DK", "DO", "DE", "EC", "EE", "SV", "FI", "FR", "GR", "GT", "HN", "HK", "HU", "IS", "IE", "IT", "LV", "LT", "LU", "MY", "MT", "MX", "NL", "NZ", "NI", "NO", "PA", "PY", "PE", "PH", "PL", "PT", "SG", "SK", "ES", "SE", "CH", "TW", "TR", "UY", "US", "GB", "AD", "LI", "MC", "ID", "JP", "TH", "VN", "RO", "IL", "ZA", "SA", "AE", "BH", "QA", "OM", "KW", "EG", "MA", "DZ", "TN", "LB", "JO", "PS", "IN", "BY", "KZ", "MD", "UA", "AL", "BA", "HR", "ME", "MK", "RS", "SI", "KR", "BD", "PK", "LK", "GH", "KE", "NG", "TZ", "UG", "AG", "AM", "BS", "BB", "BZ", "BT", "BW", "BF", "CV", "CW", "DM", "FJ", "GM", "GE", "GD", "GW", "GY", "HT", "JM", "KI", "LS", "LR", "MW", "MV", "ML", "MH", "FM", "NA", "NR", "NE", "PW", "PG", "WS", "SM", "ST", "SN", "SC", "SL", "SB", "KN", "LC", "VC", "SR", "TL", "TO", "TT", "TV", "VU", "AZ", "BN", "BI", "KH", "CM", "TD", "KM", "GQ", "SZ", "GA", "GN", "KG", "LA", "MO", "MR", "MN", "NP", "RW", "TG", "UZ", "ZW", "BJ", "MG", "MU", "MZ", "AO", "CI", "DJ", "ZM", "CD", "CG", "IQ", "LY", "TJ", "VE", "ET", "XK"], "external_urls": {"spotify": "https://open.spotify.com/album/5Arix0TdRWLdJ2Z2mzBhTD"}, "href": "https://api.spotify.com/v1/albums/5Arix0TdRWLdJ2Z2mzBhTD", "id": "5Arix0TdRWLdJ2Z2mzBhTD", "images": [{"height": 640, "url": "https://i.scdn.co/image/ab67616d0000b2733eaa6ec20fecf74f04f78c06", "width": 640}, {"height": 300, "url": "https://i.scdn.co/image/ab67616d00001e023eaa6ec20fecf74f04f78c06", "width": 300}, {"height": 64, "url": "https://i.scdn.co/image/ab67616d000048513eaa6ec20fecf74f04f78c06", "width": 64}], "name": "Haddinden Fazla", "release_date": "2017-05-17", "release_date_precision": "day", "total_tracks": 10, "type": "album", "uri": "spotify:album:5Arix0TdRWLdJ2Z2mzBhTD"}, {"album_group": "album", "album_type": "album", "artists": [{"external_urls": {"spotify": "https://open.spotify.com/artist/0Qbd0AGWuzggX61s306wZN"}, "href": "https://api.spotify.com/v1/artists/0Qbd0AGWuzggX61s306wZN", "id": "0Qbd0AGWuzggX61s306wZN", "name": "Ebru Ya\u015far", "type": "artist", "uri": "spotify:artist:0Qbd0AGWuzggX61s306wZN"}], "available_markets": ["AR", "AU", "AT", "BE", "BO", "BR", "BG", "CA", "CL", "CO", "CR", "CY", "CZ", "DK", "DO", "DE", "EC", "EE", "SV", "FI", "FR", "GR", "GT", "HN", "HK", "HU", "IS", "IE", "IT", "LV", "LT", "LU", "MY", "MT", "MX", "NL", "NZ", "NI", "NO", "PA", "PY", "PE", "PH", "PL", "PT", "SG", "SK", "ES", "SE", "CH", "TW", "TR", "UY", "US", "GB", "AD", "LI", "MC", "ID", "JP", "TH", "VN", "RO", "IL", "ZA", "SA", "AE", "BH", "QA", "OM", "KW", "EG", "MA", "DZ", "TN", "LB", "JO", "PS", "IN", "BY", "KZ", "MD", "UA", "AL", "BA", "HR", "ME", "MK", "RS", "SI", "KR", "BD", "PK", "LK", "GH", "KE", "NG", "TZ", "UG", "AG", "AM", "BS", "BB", "BZ", "BT", "BW", "BF", "CV", "CW", "DM", "FJ", "GM", "GE", "GD", "GW", "GY", "HT", "JM", "KI", "LS", "LR", "MW", "MV", "ML", "MH", "FM", "NA", "NR", "NE", "PW", "PG", "WS", "SM", "ST", "SN", "SC", "SL", "SB", "KN", "LC", "VC", "SR", "TL", "TO", "TT", "TV", "VU", "AZ", "BN", "BI", "KH", "CM", "TD", "KM", "GQ", "SZ", "GA", "GN", "KG", "LA", "MO", "MR", "MN", "NP", "RW", "TG", "UZ", "ZW", "BJ", "MG", "MU", "MZ", "AO", "CI", "DJ", "ZM", "CD", "CG", "IQ", "LY", "TJ", "VE", "ET", "XK"], "external_urls": {"spotify": "https://open.spotify.com/album/5hstXmrMR2xIjKC5rWxOXY"}, "href": "https://api.spotify.com/v1/albums/5hstXmrMR2xIjKC5rWxOXY", "id": "5hstXmrMR2xIjKC5rWxOXY", "images": [{"height": 640, "url": "https://i.scdn.co/image/ab67616d0000b273838a168adceb46f3281d48c1", "width": 640}, {"height": 300, "url": "https://i.scdn.co/image/ab67616d00001e02838a168adceb46f3281d48c1", "width": 300}, {"height": 64, "url": "https://i.scdn.co/image/ab67616d00004851838a168adceb46f3281d48c1", "width": 64}], "name": "Bu Sahilde / Vurulur D\u00fc\u015flerim", "release_date": "2015-05-05", "release_date_precision": "day", "total_tracks": 12, "type": "album", "uri": "spotify:album:5hstXmrMR2xIjKC5rWxOXY"}, {"album_group": "album", "album_type": "album", "artists": [{"external_urls": {"spotify": "https://open.spotify.com/artist/0Qbd0AGWuzggX61s306wZN"}, "href": "https://api.spotify.com/v1/artists/0Qbd0AGWuzggX61s306wZN", "id": "0Qbd0AGWuzggX61s306wZN", "name": "Ebru Ya\u015far", "type": "artist", "uri": "spotify:artist:0Qbd0AGWuzggX61s306wZN"}], "available_markets": ["AR", "AU", "AT", "BE", "BO", "BR", "BG", "CA", "CL", "CO", "CR", "CY", "CZ", "DK", "DO", "DE", "EC", "EE", "SV", "FI", "FR", "GR", "GT", "HN", "HK", "HU", "IS", "IE", "IT", "LV", "LT", "LU", "MY", "MT", "MX", "NL", "NZ", "NI", "NO", "PA", "PY", "PE", "PH", "PL", "PT", "SG", "SK", "ES", "SE", "CH", "TW", "TR", "UY", "US", "GB", "AD", "LI", "MC", "ID", "JP", "TH", "VN", "RO", "IL", "ZA", "SA", "AE", "BH", "QA", "OM", "KW", "EG", "MA", "DZ", "TN", "LB", "JO", "PS", "IN", "BY", "KZ", "MD", "UA", "AL", "BA", "HR", "ME", "MK", "RS", "SI", "KR", "BD", "PK", "LK", "GH", "KE", "NG", "TZ", "UG", "AG", "AM", "BS", "BB", "BZ", "BT", "BW", "BF", "CV", "CW", "DM", "FJ", "GM", "GE", "GD", "GW", "GY", "HT", "JM", "KI", "LS", "LR", "MW", "MV", "ML", "MH", "FM", "NA", "NR", "NE", "PW", "PG", "WS", "SM", "ST", "SN", "SC", "SL", "SB", "KN", "LC", "VC", "SR", "TL", "TO", "TT", "TV", "VU", "AZ", "BN", "BI", "KH", "CM", "TD", "KM", "GQ", "SZ", "GA", "GN", "KG", "LA", "MO", "MR", "MN", "NP", "RW", "TG", "UZ", "ZW", "BJ", "MG", "MU", "MZ", "AO", "CI", "DJ", "ZM", "CD", "CG", "IQ", "LY", "TJ", "VE", "ET", "XK"], "external_urls": {"spotify": "https://open.spotify.com/album/1Ds7UIUYyCIaGhoh7F4vW9"}, "href": "https://api.spotify.com/v1/albums/1Ds7UIUYyCIaGhoh7F4vW9", "id": "1Ds7UIUYyCIaGhoh7F4vW9", "images": [{"height": 640, "url": "https://i.scdn.co/image/ab67616d0000b27318e962d29977cd0def2cdf69", "width": 640}, {"height": 300, "url": "https://i.scdn.co/image/ab67616d00001e0218e962d29977cd0def2cdf69", "width": 300}, {"height": 64, "url": "https://i.scdn.co/image/ab67616d0000485118e962d29977cd0def2cdf69", "width": 64}], "name": "Sevenler \u00d6lmez", "release_date": "2015-05-01", "release_date_precision": "day", "total_tracks": 10, "type": "album", "uri": "spotify:album:1Ds7UIUYyCIaGhoh7F4vW9"}, {"album_group": "album", "album_type": "album", "artists": [{"external_urls": {"spotify": "https://open.spotify.com/artist/0Qbd0AGWuzggX61s306wZN"}, "href": "https://api.spotify.com/v1/artists/0Qbd0AGWuzggX61s306wZN", "id": "0Qbd0AGWuzggX61s306wZN", "name": "Ebru Ya\u015far", "type": "artist", "uri": "spotify:artist:0Qbd0AGWuzggX61s306wZN"}], "available_markets": ["AR", "AU", "AT", "BE", "BO", "BR", "BG", "CA", "CL", "CO", "CR", "CY", "CZ", "DK", "DO", "DE", "EC", "EE", "SV", "FI", "FR", "GR", "GT", "HN", "HK", "HU", "IS", "IE", "IT", "LV", "LT", "LU", "MY", "MT", "MX", "NL", "NZ", "NI", "NO", "PA", "PY", "PE", "PH", "PL", "PT", "SG", "SK", "ES", "SE", "CH", "TW", "TR", "UY", "US", "GB", "AD", "LI", "MC", "ID", "JP", "TH", "VN", "RO", "IL", "ZA", "SA", "AE", "BH", "QA", "OM", "KW", "EG", "MA", "DZ", "TN", "LB", "JO", "PS", "IN", "BY", "KZ", "MD", "UA", "AL", "BA", "HR", "ME", "MK", "RS", "SI", "KR", "BD", "PK", "LK", "GH", "KE", "NG", "TZ", "UG", "AG", "AM", "BS", "BB", "BZ", "BT", "BW", "BF", "CV", "CW", "DM", "FJ", "GM", "GE", "GD", "GW", "GY", "HT", "JM", "KI", "LS", "LR", "MW", "MV", "ML", "MH", "FM", "NA", "NR", "NE", "PW", "PG", "WS", "SM", "ST", "SN", "SC", "SL", "SB", "KN", "LC", "VC", "SR", "TL", "TO", "TT", "TV", "VU", "AZ", "BN", "BI", "KH", "CM", "TD", "KM", "GQ", "SZ", "GA", "GN", "KG", "LA", "MO", "MR", "MN", "NP", "RW", "TG", "UZ", "ZW", "BJ", "MG", "MU", "MZ", "AO", "CI", "DJ", "ZM", "CD", "CG", "IQ", "LY", "TJ", "VE", "ET", "XK"], "external_urls": {"spotify": "https://open.spotify.com/album/77lqDMhtnFqfQ1KoWgLMmi"}, "href": "https://api.spotify.com/v1/albums/77lqDMhtnFqfQ1KoWgLMmi", "id": "77lqDMhtnFqfQ1KoWgLMmi", "images": [{"height": 640, "url": "https://i.scdn.co/image/ab67616d0000b273251e684ae032854900a01668", "width": 640}, {"height": 300, "url": "https://i.scdn.co/image/ab67616d00001e02251e684ae032854900a01668", "width": 300}, {"height": 64, "url": "https://i.scdn.co/image/ab67616d00004851251e684ae032854900a01668", "width": 64}], "name": "Delidir", "release_date": "2011-06-22", "release_date_precision": "day", "total_tracks": 13, "type": "album", "uri": "spotify:album:77lqDMhtnFqfQ1KoWgLMmi"}, {"album_group": "album", "album_type": "album", "artists": [{"external_urls": {"spotify": "https://open.spotify.com/artist/0Qbd0AGWuzggX61s306wZN"}, "href": "https://api.spotify.com/v1/artists/0Qbd0AGWuzggX61s306wZN", "id": "0Qbd0AGWuzggX61s306wZN", "name": "Ebru Ya\u015far", "type": "artist", "uri": "spotify:artist:0Qbd0AGWuzggX61s306wZN"}], "available_markets": ["AR", "AU", "AT", "BE", "BO", "BR", "BG", "CA", "CL", "CO", "CR", "CY", "CZ", "DK", "DO", "DE", "EC", "EE", "SV", "FI", "FR", "GR", "GT", "HN", "HK", "HU", "IS", "IE", "IT", "LV", "LT", "LU", "MY", "MT", "MX", "NL", "NZ", "NI", "NO", "PA", "PY", "PE", "PH", "PL", "PT", "SG", "SK", "ES", "SE", "CH", "TW", "TR", "UY", "US", "GB", "AD", "LI", "MC", "ID", "JP", "TH", "VN", "RO", "IL", "ZA", "SA", "AE", "BH", "QA", "OM", "KW", "EG", "MA", "DZ", "TN", "LB", "JO", "PS", "IN", "BY", "KZ", "MD", "UA", "AL", "BA", "HR", "ME", "MK", "RS", "SI", "KR", "BD", "PK", "LK", "GH", "KE", "NG", "TZ", "UG", "AG", "AM", "BS", "BB", "BZ", "BT", "BW", "BF", "CV", "CW", "DM", "FJ", "GM", "GE", "GD", "GW", "GY", "HT", "JM", "KI", "LS", "LR", "MW", "MV", "ML", "MH", "FM", "NA", "NR", "NE", "PW", "PG", "WS", "SM", "ST", "SN", "SC", "SL", "SB", "KN", "LC", "VC", "SR", "TL", "TO", "TT", "TV", "VU", "AZ", "BN", "BI", "KH", "CM", "TD", "KM", "GQ", "SZ", "GA", "GN", "KG", "LA", "MO", "MR", "MN", "NP", "RW", "TG", "UZ", "ZW", "BJ", "MG", "MU", "MZ", "AO", "CI", "DJ", "ZM", "CD", "CG", "IQ", "LY", "TJ", "VE", "ET", "XK"], "external_urls": {"spotify": "https://open.spotify.com/album/4wsgc4WWqVqVJuAMGgIYeA"}, "href": "https://api.spotify.com/v1/albums/4wsgc4WWqVqVJuAMGgIYeA", "id": "4wsgc4WWqVqVJuAMGgIYeA", "images": [{"height": 640, "url": "https://i.scdn.co/image/ab67616d0000b27360e529ed92a86b60e9c053e2", "width": 640}, {"height": 300, "url": "https://i.scdn.co/image/ab67616d00001e0260e529ed92a86b60e9c053e2", "width": 300}, {"height": 64, "url": "https://i.scdn.co/image/ab67616d0000485160e529ed92a86b60e9c053e2", "width": 64}], "name": "Seviyorum Seni", "release_date": "2008-11-24", "release_date_precision": "day", "total_tracks": 10, "type": "album", "uri": "spotify:album:4wsgc4WWqVqVJuAMGgIYeA"}, {"album_group": "album", "album_type": "album", "artists": [{"external_urls": {"spotify": "https://open.spotify.com/artist/0Qbd0AGWuzggX61s306wZN"}, "href": "https://api.spotify.com/v1/artists/0Qbd0AGWuzggX61s306wZN", "id": "0Qbd0AGWuzggX61s306wZN", "name": "Ebru Ya\u015far", "type": "artist", "uri": "spotify:artist:0Qbd0AGWuzggX61s306wZN"}], "available_markets": ["AR", "AU", "AT", "BE", "BO", "BR", "BG", "CA", "CL", "CO", "CR", "CY", "CZ", "DK", "DO", "DE", "EC", "EE", "SV", "FI", "FR", "GR", "GT", "HN", "HK", "HU", "IS", "IE", "IT", "LV", "LT", "LU", "MY", "MT", "MX", "NL", "NZ", "NI", "NO", "PA", "PY", "PE", "PH", "PL", "PT", "SG", "SK", "ES", "SE", "CH", "TW", "TR", "UY", "US", "GB", "AD", "LI", "MC", "ID", "JP", "TH", "VN", "RO", "IL", "ZA", "SA", "AE", "BH", "QA", "OM", "KW", "EG", "MA", "DZ", "TN", "LB", "JO", "PS", "IN", "BY", "KZ", "MD", "UA", "AL", "BA", "HR", "ME", "MK", "RS", "SI", "KR", "BD", "PK", "LK", "GH", "KE", "NG", "TZ", "UG", "AG", "AM", "BS", "BB", "BZ", "BT", "BW", "BF", "CV", "CW", "DM", "FJ", "GM", "GE", "GD", "GW", "GY", "HT", "JM", "KI", "LS", "LR", "MW", "MV", "ML", "MH", "FM", "NA", "NR", "NE", "PW", "PG", "WS", "SM", "ST", "SN", "SC", "SL", "SB", "KN", "LC", "VC", "SR", "TL", "TO", "TT", "TV", "VU", "AZ", "BN", "BI", "KH", "CM", "TD", "KM", "GQ", "SZ", "GA", "GN", "KG", "LA", "MO", "MR", "MN", "NP", "RW", "TG", "UZ", "ZW", "BJ", "MG", "MU", "MZ", "AO", "CI", "DJ", "ZM", "CD", "CG", "IQ", "LY", "TJ", "VE", "ET", "XK"], "external_urls": {"spotify": "https://open.spotify.com/album/2vI1QQEbFXctPOhOmf6hrF"}, "href": "https://api.spotify.com/v1/albums/2vI1QQEbFXctPOhOmf6hrF", "id": "2vI1QQEbFXctPOhOmf6hrF", "images": [{"height": 640, "url": "https://i.scdn.co/image/ab67616d0000b273012fa92281607f242e4fe723", "width": 640}, {"height": 300, "url": "https://i.scdn.co/image/ab67616d00001e02012fa92281607f242e4fe723", "width": 300}, {"height": 64, "url": "https://i.scdn.co/image/ab67616d00004851012fa92281607f242e4fe723", "width": 64}], "name": "Ye\u015fillenirim", "release_date": "2006", "release_date_precision": "year", "total_tracks": 16, "type": "album", "uri": "spotify:album:2vI1QQEbFXctPOhOmf6hrF"}, {"album_group": "album", "album_type": "album", "artists": [{"external_urls": {"spotify": "https://open.spotify.com/artist/0Qbd0AGWuzggX61s306wZN"}, "href": "https://api.spotify.com/v1/artists/0Qbd0AGWuzggX61s306wZN", "id": "0Qbd0AGWuzggX61s306wZN", "name": "Ebru Ya\u015far", "type": "artist", "uri": "spotify:artist:0Qbd0AGWuzggX61s306wZN"}], "available_markets": ["AR", "AU", "AT", "BE", "BO", "BR", "BG", "CA", "CL", "CO", "CR", "CY", "CZ", "DK", "DO", "DE", "EC", "EE", "SV", "FI", "FR", "GR", "GT", "HN", "HK", "HU", "IS", "IE", "IT", "LV", "LT", "LU", "MY", "MT", "MX", "NL", "NZ", "NI", "NO", "PA", "PY", "PE", "PH", "PL", "PT", "SG", "SK", "ES", "SE", "CH", "TW", "TR", "UY", "US", "GB", "AD", "LI", "MC", "ID", "JP", "TH", "VN", "RO", "IL", "ZA", "SA", "AE", "BH", "QA", "OM", "KW", "EG", "MA", "DZ", "TN", "LB", "JO", "PS", "IN", "BY", "KZ", "MD", "UA", "AL", "BA", "HR", "ME", "MK", "RS", "SI", "KR", "BD", "PK", "LK", "GH", "KE", "NG", "TZ", "UG", "AG", "AM", "BS", "BB", "BZ", "BT", "BW", "BF", "CV", "CW", "DM", "FJ", "GM", "GE", "GD", "GW", "GY", "HT", "JM", "KI", "LS", "LR", "MW", "MV", "ML", "MH", "FM", "NA", "NR", "NE", "PW", "PG", "WS", "SM", "ST", "SN", "SC", "SL", "SB", "KN", "LC", "VC", "SR", "TL", "TO", "TT", "TV", "VU", "AZ", "BN", "BI", "KH", "CM", "TD", "KM", "GQ", "SZ", "GA", "GN", "KG", "LA", "MO", "MR", "MN", "NP", "RW", "TG", "UZ", "ZW", "BJ", "MG", "MU", "MZ", "AO", "CI", "DJ", "ZM", "CD", "CG", "IQ", "LY", "TJ", "VE", "ET", "XK"], "external_urls": {"spotify": "https://open.spotify.com/album/3kbyXiiebyv8hM6oGXtSsN"}, "href": "https://api.spotify.com/v1/albums/3kbyXiiebyv8hM6oGXtSsN", "id": "3kbyXiiebyv8hM6oGXtSsN", "images": [{"height": 640, "url": "https://i.scdn.co/image/ab67616d0000b273cb908d8515f0379ba47b231b", "width": 640}, {"height": 300, "url": "https://i.scdn.co/image/ab67616d00001e02cb908d8515f0379ba47b231b", "width": 300}, {"height": 64, "url": "https://i.scdn.co/image/ab67616d00004851cb908d8515f0379ba47b231b", "width": 64}], "name": "A\u015fk\u0131m\u0131z Buraya Kadar", "release_date": "2003-05-28", "release_date_precision": "day", "total_tracks": 13, "type": "album", "uri": "spotify:album:3kbyXiiebyv8hM6oGXtSsN"}, {"album_group": "album", "album_type": "album", "artists": [{"external_urls": {"spotify": "https://open.spotify.com/artist/0Qbd0AGWuzggX61s306wZN"}, "href": "https://api.spotify.com/v1/artists/0Qbd0AGWuzggX61s306wZN", "id": "0Qbd0AGWuzggX61s306wZN", "name": "Ebru Ya\u015far", "type": "artist", "uri": "spotify:artist:0Qbd0AGWuzggX61s306wZN"}], "available_markets": ["AR", "AU", "AT", "BE", "BO", "BR", "BG", "CA", "CL", "CO", "CR", "CY", "CZ", "DK", "DO", "DE", "EC", "EE", "SV", "FI", "FR", "GR", "GT", "HN", "HK", "HU", "IS", "IE", "IT", "LV", "LT", "LU", "MY", "MT", "MX", "NL", "NZ", "NI", "NO", "PA", "PY", "PE", "PH", "PL", "PT", "SG", "SK", "ES", "SE", "CH", "TW", "TR", "UY", "US", "GB", "AD", "LI", "MC", "ID", "JP", "TH", "VN", "RO", "IL", "ZA", "SA", "AE", "BH", "QA", "OM", "KW", "EG", "MA", "DZ", "TN", "LB", "JO", "PS", "IN", "BY", "KZ", "MD", "UA", "AL", "BA", "HR", "ME", "MK", "RS", "SI", "KR", "BD", "PK", "LK", "GH", "KE", "NG", "TZ", "UG", "AG", "AM", "BS", "BB", "BZ", "BT", "BW", "BF", "CV", "CW", "DM", "FJ", "GM", "GE", "GD", "GW", "GY", "HT", "JM", "KI", "LS", "LR", "MW", "MV", "ML", "MH", "FM", "NA", "NR", "NE", "PW", "PG", "WS", "SM", "ST", "SN", "SC", "SL", "SB", "KN", "LC", "VC", "SR", "TL", "TO", "TT", "TV", "VU", "AZ", "BN", "BI", "KH", "CM", "TD", "KM", "GQ", "SZ", "GA", "GN", "KG", "LA", "MO", "MR", "MN", "NP", "RW", "TG", "UZ", "ZW", "BJ", "MG", "MU", "MZ", "AO", "CI", "DJ", "ZM", "CD", "CG", "IQ", "LY", "TJ", "VE", "ET", "XK"], "external_urls": {"spotify": "https://open.spotify.com/album/0wJhJmb0Fnnd22v2w9cmgX"}, "href": "https://api.spotify.com/v1/albums/0wJhJmb0Fnnd22v2w9cmgX", "id": "0wJhJmb0Fnnd22v2w9cmgX", "images": [{"height": 640, "url": "https://i.scdn.co/image/ab67616d0000b2738d91b6214b7e18e75e20b33c", "width": 640}, {"height": 300, "url": "https://i.scdn.co/image/ab67616d00001e028d91b6214b7e18e75e20b33c", "width": 300}, {"height": 64, "url": "https://i.scdn.co/image/ab67616d000048518d91b6214b7e18e75e20b33c", "width": 64}], "name": "Seni Anan Benim I\u00e7in Do\u011furmu\u015f", "release_date": "1999-06-07", "release_date_precision": "day", "total_tracks": 14, "type": "album", "uri": "spotify:album:0wJhJmb0Fnnd22v2w9cmgX"}, {"album_group": "album", "album_type": "album", "artists": [{"external_urls": {"spotify": "https://open.spotify.com/artist/0Qbd0AGWuzggX61s306wZN"}, "href": "https://api.spotify.com/v1/artists/0Qbd0AGWuzggX61s306wZN", "id": "0Qbd0AGWuzggX61s306wZN", "name": "Ebru Ya\u015far", "type": "artist", "uri": "spotify:artist:0Qbd0AGWuzggX61s306wZN"}], "available_markets": ["AR", "AU", "AT", "BE", "BO", "BR", "BG", "CA", "CL", "CO", "CR", "CY", "CZ", "DK", "DO", "DE", "EC", "EE", "SV", "FI", "FR", "GR", "GT", "HN", "HK", "HU", "IS", "IE", "IT", "LV", "LT", "LU", "MY", "MT", "MX", "NL", "NZ", "NI", "NO", "PA", "PY", "PE", "PH", "PL", "PT", "SG", "SK", "ES", "SE", "CH", "TW", "TR", "UY", "US", "GB", "AD", "LI", "MC", "ID", "JP", "TH", "VN", "RO", "IL", "ZA", "SA", "AE", "BH", "QA", "OM", "KW", "EG", "MA", "DZ", "TN", "LB", "JO", "PS", "IN", "BY", "KZ", "MD", "UA", "AL", "BA", "HR", "ME", "MK", "RS", "SI", "KR", "BD", "PK", "LK", "GH", "KE", "NG", "TZ", "UG", "AG", "AM", "BS", "BB", "BZ", "BT", "BW", "BF", "CV", "CW", "DM", "FJ", "GM", "GE", "GD", "GW", "GY", "HT", "JM", "KI", "LS", "LR", "MW", "MV", "ML", "MH", "FM", "NA", "NR", "NE", "PW", "PG", "WS", "SM", "ST", "SN", "SC", "SL", "SB", "KN", "LC", "VC", "SR", "TL", "TO", "TT", "TV", "VU", "AZ", "BN", "BI", "KH", "CM", "TD", "KM", "GQ", "SZ", "GA", "GN", "KG", "LA", "MO", "MR", "MN", "NP", "RW", "TG", "UZ", "ZW", "BJ", "MG", "MU", "MZ", "AO", "CI", "DJ", "ZM", "CD", "CG", "IQ", "LY", "TJ", "VE", "ET", "XK"], "external_urls": {"spotify": "https://open.spotify.com/album/0YOXR7n1XL2jJR4QKtQCrh"}, "href": "https://api.spotify.com/v1/albums/0YOXR7n1XL2jJR4QKtQCrh", "id": "0YOXR7n1XL2jJR4QKtQCrh", "images": [{"height": 640, "url": "https://i.scdn.co/image/ab67616d0000b273a49f5e83089373cdb0ad5d15", "width": 640}, {"height": 300, "url": "https://i.scdn.co/image/ab67616d00001e02a49f5e83089373cdb0ad5d15", "width": 300}, {"height": 64, "url": "https://i.scdn.co/image/ab67616d00004851a49f5e83089373cdb0ad5d15", "width": 64}], "name": "Sanat-\u0131 Ebru", "release_date": "1990", "release_date_precision": "year", "total_tracks": 11, "type": "album", "uri": "spotify:album:0YOXR7n1XL2jJR4QKtQCrh"}, {"album_group": "single", "album_type": "single", "artists": [{"external_urls": {"spotify": "https://open.spotify.com/artist/0Qbd0AGWuzggX61s306wZN"}, "href": "https://api.spotify.com/v1/artists/0Qbd0AGWuzggX61s306wZN", "id": "0Qbd0AGWuzggX61s306wZN", "name": "Ebru Ya\u015far", "type": "artist", "uri": "spotify:artist:0Qbd0AGWuzggX61s306wZN"}, {"external_urls": {"spotify": "https://open.spotify.com/artist/20VUzeHAjxKUEJuXT6EiMo"}, "href": "https://api.spotify.com/v1/artists/20VUzeHAjxKUEJuXT6EiMo", "id": "20VUzeHAjxKUEJuXT6EiMo", "name": "Siyam", "type": "artist", "uri": "spotify:artist:20VUzeHAjxKUEJuXT6EiMo"}], "available_markets": ["AR", "AU", "AT", "BE", "BO", "BR", "BG", "CA", "CL", "CO", "CR", "CY", "CZ", "DK", "DO", "DE", "EC", "EE", "SV", "FI", "FR", "GR", "GT", "HN", "HK", "HU", "IS", "IE", "IT", "LV", "LT", "LU", "MY", "MT", "MX", "NL", "NZ", "NI", "NO", "PA", "PY", "PE", "PH", "PL", "PT", "SG", "SK", "ES", "SE", "CH", "TW", "TR", "UY", "US", "GB", "AD", "LI", "MC", "ID", "JP", "TH", "VN", "RO", "IL", "ZA", "SA", "AE", "BH", "QA", "OM", "KW", "EG", "MA", "DZ", "TN", "LB", "JO", "PS", "IN", "BY", "KZ", "MD", "UA", "AL", "BA", "HR", "ME", "MK", "RS", "SI", "KR", "BD", "PK", "LK", "GH", "KE", "NG", "TZ", "UG", "AG", "AM", "BS", "BB", "BZ", "BT", "BW", "BF", "CV", "CW", "DM", "FJ", "GM", "GE", "GD", "GW", "GY", "HT", "JM", "KI", "LS", "LR", "MW", "MV", "ML", "MH", "FM", "NA", "NR", "NE", "PW", "PG", "WS", "SM", "ST", "SN", "SC", "SL", "SB", "KN", "LC", "VC", "SR", "TL", "TO", "TT", "TV", "VU", "AZ", "BN", "BI", "KH", "CM", "TD", "KM", "GQ", "SZ", "GA", "GN", "KG", "LA", "MO", "MR", "MN", "NP", "RW", "TG", "UZ", "ZW", "BJ", "MG", "MU", "MZ", "AO", "CI", "DJ", "ZM", "CD", "CG", "IQ", "LY", "TJ", "VE", "ET", "XK"], "external_urls": {"spotify": "https://open.spotify.com/album/5l3AhfIKrcdqJiYUMySwNb"}, "href": "https://api.spotify.com/v1/albums/5l3AhfIKrcdqJiYUMySwNb", "id": "5l3AhfIKrcdqJiYUMySwNb", "images": [{"height": 640, "url": "https://i.scdn.co/image/ab67616d0000b273dea79d76c3edfa06158c5c52", "width": 640}, {"height": 300, "url": "https://i.scdn.co/image/ab67616d00001e02dea79d76c3edfa06158c5c52", "width": 300}, {"height": 64, "url": "https://i.scdn.co/image/ab67616d00004851dea79d76c3edfa06158c5c52", "width": 64}], "name": "Yoksun", "release_date": "2024-02-02", "release_date_precision": "day", "total_tracks": 1, "type": "album", "uri": "spotify:album:5l3AhfIKrcdqJiYUMySwNb"}, {"album_group": "single", "album_type": "single", "artists": [{"external_urls": {"spotify": "https://open.spotify.com/artist/7FvMAbdiffitFmbuJN3Vsk"}, "href": "https://api.spotify.com/v1/artists/7FvMAbdiffitFmbuJN3Vsk", "id": "7FvMAbdiffitFmbuJN3Vsk", "name": "Emrah Karaduman", "type": "artist", "uri": "spotify:artist:7FvMAbdiffitFmbuJN3Vsk"}, {"external_urls": {"spotify": "https://open.spotify.com/artist/0Qbd0AGWuzggX61s306wZN"}, "href": "https://api.spotify.com/v1/artists/0Qbd0AGWuzggX61s306wZN", "id": "0Qbd0AGWuzggX61s306wZN", "name": "Ebru Ya\u015far", "type": "artist", "uri": "spotify:artist:0Qbd0AGWuzggX61s306wZN"}], "available_markets": ["AR", "AU", "AT", "BE", "BO", "BR", "BG", "CA", "CL", "CO", "CR", "CY", "CZ", "DK", "DO", "DE", "EC", "EE", "SV", "FI", "FR", "GR", "GT", "HN", "HK", "HU", "IS", "IE", "IT", "LV", "LT", "LU", "MY", "MT", "MX", "NL", "NZ", "NI", "NO", "PA", "PY", "PE", "PH", "PL", "PT", "SG", "SK", "ES", "SE", "CH", "TW", "TR", "UY", "US", "GB", "AD", "LI", "MC", "ID", "JP", "TH", "VN", "RO", "IL", "ZA", "SA", "AE", "BH", "QA", "OM", "KW", "EG", "MA", "DZ", "TN", "LB", "JO", "PS", "IN", "BY", "KZ", "MD", "UA", "AL", "BA", "HR", "ME", "MK", "RS", "SI", "KR", "BD", "PK", "LK", "GH", "KE", "NG", "TZ", "UG", "AG", "AM", "BS", "BB", "BZ", "BT", "BW", "BF", "CV", "CW", "DM", "FJ", "GM", "GE", "GD", "GW", "GY", "HT", "JM", "KI", "LS", "LR", "MW", "MV", "ML", "MH", "FM", "NA", "NR", "NE", "PW", "PG", "WS", "SM", "ST", "SN", "SC", "SL", "SB", "KN", "LC", "VC", "SR", "TL", "TO", "TT", "TV", "VU", "AZ", "BN", "BI", "KH", "CM", "TD", "KM", "GQ", "SZ", "GA", "GN", "KG", "LA", "MO", "MR", "MN", "NP", "RW", "TG", "UZ", "ZW", "BJ", "MG", "MU", "MZ", "AO", "CI", "DJ", "ZM", "CD", "CG", "IQ", "LY", "TJ", "VE", "ET", "XK"], "external_urls": {"spotify": "https://open.spotify.com/album/7Czvqf55bjy35aC8sg8RIR"}, "href": "https://api.spotify.com/v1/albums/7Czvqf55bjy35aC8sg8RIR", "id": "7Czvqf55bjy35aC8sg8RIR", "images": [{"height": 640, "url": "https://i.scdn.co/image/ab67616d0000b27387693b90d3f4365c650c3769", "width": 640}, {"height": 300, "url": "https://i.scdn.co/image/ab67616d00001e0287693b90d3f4365c650c3769", "width": 300}, {"height": 64, "url": "https://i.scdn.co/image/ab67616d0000485187693b90d3f4365c650c3769", "width": 64}], "name": "En G\u00fczel Yenilgim (Akustik)", "release_date": "2024-01-05", "release_date_precision": "day", "total_tracks": 1, "type": "album", "uri": "spotify:album:7Czvqf55bjy35aC8sg8RIR"}, {"album_group": "single", "album_type": "single", "artists": [{"external_urls": {"spotify": "https://open.spotify.com/artist/2a2YSCx78HHWVOsCuMpeXz"}, "href": "https://api.spotify.com/v1/artists/2a2YSCx78HHWVOsCuMpeXz", "id": "2a2YSCx78HHWVOsCuMpeXz", "name": "Burak Bulut", "type": "artist", "uri": "spotify:artist:2a2YSCx78HHWVOsCuMpeXz"}, {"external_urls": {"spotify": "https://open.spotify.com/artist/0Qbd0AGWuzggX61s306wZN"}, "href": "https://api.spotify.com/v1/artists/0Qbd0AGWuzggX61s306wZN", "id": "0Qbd0AGWuzggX61s306wZN", "name": "Ebru Ya\u015far", "type": "artist", "uri": "spotify:artist:0Qbd0AGWuzggX61s306wZN"}], "available_markets": ["AR", "AU", "AT", "BE", "BO", "BR", "BG", "CA", "CL", "CO", "CR", "CY", "CZ", "DK", "DO", "DE", "EC", "EE", "SV", "FI", "FR", "GR", "GT", "HN", "HK", "HU", "IS", "IE", "IT", "LV", "LT", "LU", "MY", "MT", "MX", "NL", "NZ", "NI", "NO", "PA", "PY", "PE", "PH", "PL", "PT", "SG", "SK", "ES", "SE", "CH", "TW", "TR", "UY", "US", "GB", "AD", "LI", "MC", "ID", "JP", "TH", "VN", "RO", "IL", "ZA", "SA", "AE", "BH", "QA", "OM", "KW", "EG", "MA", "DZ", "TN", "LB", "JO", "PS", "IN", "BY", "KZ", "MD", "UA", "AL", "BA", "HR", "ME", "MK", "RS", "SI", "KR", "BD", "PK", "LK", "GH", "KE", "NG", "TZ", "UG", "AG", "AM", "BS", "BB", "BZ", "BT", "BW", "BF", "CV", "CW", "DM", "FJ", "GM", "GE", "GD", "GW", "GY", "HT", "JM", "KI", "LS", "LR", "MW", "MV", "ML", "MH", "FM", "NA", "NR", "NE", "PW", "PG", "WS", "SM", "ST", "SN", "SC", "SL", "SB", "KN", "LC", "VC", "SR", "TL", "TO", "TT", "TV", "VU", "AZ", "BN", "BI", "KH", "CM", "TD", "KM", "GQ", "SZ", "GA", "GN", "KG", "LA", "MO", "MR", "MN", "NP", "RW", "TG", "UZ", "ZW", "BJ", "MG", "MU", "MZ", "AO", "CI", "DJ", "ZM", "CD", "CG", "IQ", "LY", "TJ", "VE", "ET", "XK"], "external_urls": {"spotify": "https://open.spotify.com/album/2vJqCgVaPM5YpMlp9laiEX"}, "href": "https://api.spotify.com/v1/albums/2vJqCgVaPM5YpMlp9laiEX", "id": "2vJqCgVaPM5YpMlp9laiEX", "images": [{"height": 640, "url": "https://i.scdn.co/image/ab67616d0000b27316efbc7804976ba4113235b5", "width": 640}, {"height": 300, "url": "https://i.scdn.co/image/ab67616d00001e0216efbc7804976ba4113235b5", "width": 300}, {"height": 64, "url": "https://i.scdn.co/image/ab67616d0000485116efbc7804976ba4113235b5", "width": 64}], "name": "Kehribar", "release_date": "2023-09-29", "release_date_precision": "day", "total_tracks": 1, "type": "album", "uri": "spotify:album:2vJqCgVaPM5YpMlp9laiEX"}, {"album_group": "single", "album_type": "single", "artists": [{"external_urls": {"spotify": "https://open.spotify.com/artist/2a2YSCx78HHWVOsCuMpeXz"}, "href": "https://api.spotify.com/v1/artists/2a2YSCx78HHWVOsCuMpeXz", "id": "2a2YSCx78HHWVOsCuMpeXz", "name": "Burak Bulut", "type": "artist", "uri": "spotify:artist:2a2YSCx78HHWVOsCuMpeXz"}, {"external_urls": {"spotify": "https://open.spotify.com/artist/0Qbd0AGWuzggX61s306wZN"}, "href": "https://api.spotify.com/v1/artists/0Qbd0AGWuzggX61s306wZN", "id": "0Qbd0AGWuzggX61s306wZN", "name": "Ebru Ya\u015far", "type": "artist", "uri": "spotify:artist:0Qbd0AGWuzggX61s306wZN"}, {"external_urls": {"spotify": "https://open.spotify.com/artist/4jF4tHJlYKS5Z9xdEatCfq"}, "href": "https://api.spotify.com/v1/artists/4jF4tHJlYKS5Z9xdEatCfq", "id": "4jF4tHJlYKS5Z9xdEatCfq", "name": "Kurtulu\u015f Ku\u015f", "type": "artist", "uri": "spotify:artist:4jF4tHJlYKS5Z9xdEatCfq"}], "available_markets": ["AR", "AU", "AT", "BE", "BO", "BR", "BG", "CA", "CL", "CO", "CR", "CY", "CZ", "DK", "DO", "DE", "EC", "EE", "SV", "FI", "FR", "GR", "GT", "HN", "HK", "HU", "IS", "IE", "IT", "LV", "LT", "LU", "MY", "MT", "MX", "NL", "NZ", "NI", "NO", "PA", "PY", "PE", "PH", "PL", "PT", "SG", "SK", "ES", "SE", "CH", "TW", "TR", "UY", "US", "GB", "AD", "LI", "MC", "ID", "JP", "TH", "VN", "RO", "IL", "ZA", "SA", "AE", "BH", "QA", "OM", "KW", "EG", "MA", "DZ", "TN", "LB", "JO", "PS", "IN", "BY", "KZ", "MD", "UA", "AL", "BA", "HR", "ME", "MK", "RS", "SI", "KR", "BD", "PK", "LK", "GH", "KE", "NG", "TZ", "UG", "AG", "AM", "BS", "BB", "BZ", "BT", "BW", "BF", "CV", "CW", "DM", "FJ", "GM", "GE", "GD", "GW", "GY", "HT", "JM", "KI", "LS", "LR", "MW", "MV", "ML", "MH", "FM", "NA", "NR", "NE", "PW", "PG", "WS", "SM", "ST", "SN", "SC", "SL", "SB", "KN", "LC", "VC", "SR", "TL", "TO", "TT", "TV", "VU", "AZ", "BN", "BI", "KH", "CM", "TD", "KM", "GQ", "SZ", "GA", "GN", "KG", "LA", "MO", "MR", "MN", "NP", "RW", "TG", "UZ", "ZW", "BJ", "MG", "MU", "MZ", "AO", "CI", "DJ", "ZM", "CD", "CG", "IQ", "LY", "TJ", "VE", "ET", "XK"], "external_urls": {"spotify": "https://open.spotify.com/album/7caYzMyzWotKVnu2xmHLQj"}, "href": "https://api.spotify.com/v1/albums/7caYzMyzWotKVnu2xmHLQj", "id": "7caYzMyzWotKVnu2xmHLQj", "images": [{"height": 640, "url": "https://i.scdn.co/image/ab67616d0000b273328be7a1b2834a911751abbc", "width": 640}, {"height": 300, "url": "https://i.scdn.co/image/ab67616d00001e02328be7a1b2834a911751abbc", "width": 300}, {"height": 64, "url": "https://i.scdn.co/image/ab67616d00004851328be7a1b2834a911751abbc", "width": 64}], "name": "\u0130\u00e7ime Ata Ata", "release_date": "2021-12-09", "release_date_precision": "day", "total_tracks": 1, "type": "album", "uri": "spotify:album:7caYzMyzWotKVnu2xmHLQj"}, {"album_group": "single", "album_type": "single", "artists": [{"external_urls": {"spotify": "https://open.spotify.com/artist/0Qbd0AGWuzggX61s306wZN"}, "href": "https://api.spotify.com/v1/artists/0Qbd0AGWuzggX61s306wZN", "id": "0Qbd0AGWuzggX61s306wZN", "name": "Ebru Ya\u015far", "type": "artist", "uri": "spotify:artist:0Qbd0AGWuzggX61s306wZN"}], "available_markets": ["AR", "AU", "AT", "BE", "BO", "BR", "BG", "CA", "CL", "CO", "CR", "CY", "CZ", "DK", "DO", "DE", "EC", "EE", "SV", "FI", "FR", "GR", "GT", "HN", "HK", "HU", "IS", "IE", "IT", "LV", "LT", "LU", "MY", "MT", "MX", "NL", "NZ", "NI", "NO", "PA", "PY", "PE", "PH", "PL", "PT", "SG", "SK", "ES", "SE", "CH", "TW", "TR", "UY", "US", "GB", "AD", "LI", "MC", "ID", "JP", "TH", "VN", "RO", "IL", "ZA", "SA", "AE", "BH", "QA", "OM", "KW", "EG", "MA", "DZ", "TN", "LB", "JO", "PS", "IN", "BY", "KZ", "MD", "UA", "AL", "BA", "HR", "ME", "MK", "RS", "SI", "KR", "BD", "PK", "LK", "GH", "KE", "NG", "TZ", "UG", "AG", "AM", "BS", "BB", "BZ", "BT", "BW", "BF", "CV", "CW", "DM", "FJ", "GM", "GE", "GD", "GW", "GY", "HT", "JM", "KI", "LS", "LR", "MW", "MV", "ML", "MH", "FM", "NA", "NR", "NE", "PW", "PG", "WS", "SM", "ST", "SN", "SC", "SL", "SB", "KN", "LC", "VC", "SR", "TL", "TO", "TT", "TV", "VU", "AZ", "BN", "BI", "KH", "CM", "TD", "KM", "GQ", "SZ", "GA", "GN", "KG", "LA", "MO", "MR", "MN", "NP", "RW", "TG", "UZ", "ZW", "BJ", "MG", "MU", "MZ", "AO", "CI", "DJ", "ZM", "CD", "CG", "IQ", "LY", "TJ", "VE", "ET", "XK"], "external_urls": {"spotify": "https://open.spotify.com/album/4GjV4XemriCJxXWDF3tjtk"}, "href": "https://api.spotify.com/v1/albums/4GjV4XemriCJxXWDF3tjtk", "id": "4GjV4XemriCJxXWDF3tjtk", "images": [{"height": 640, "url": "https://i.scdn.co/image/ab67616d0000b2730cd0ba1fa06b09e77e3d3ce5", "width": 640}, {"height": 300, "url": "https://i.scdn.co/image/ab67616d00001e020cd0ba1fa06b09e77e3d3ce5", "width": 300}, {"height": 64, "url": "https://i.scdn.co/image/ab67616d000048510cd0ba1fa06b09e77e3d3ce5", "width": 64}], "name": "Kalmam", "release_date": "2020-03-11", "release_date_precision": "day", "total_tracks": 1, "type": "album", "uri": "spotify:album:4GjV4XemriCJxXWDF3tjtk"}, {"album_group": "single", "album_type": "single", "artists": [{"external_urls": {"spotify": "https://open.spotify.com/artist/0Qbd0AGWuzggX61s306wZN"}, "href": "https://api.spotify.com/v1/artists/0Qbd0AGWuzggX61s306wZN", "id": "0Qbd0AGWuzggX61s306wZN", "name": "Ebru Ya\u015far", "type": "artist", "uri": "spotify:artist:0Qbd0AGWuzggX61s306wZN"}], "available_markets": ["AR", "AU", "AT", "BE", "BO", "BR", "BG", "CA", "CL", "CO", "CR", "CY", "CZ", "DK", "DO", "DE", "EC", "EE", "SV", "FI", "FR", "GR", "GT", "HN", "HK", "HU", "IS", "IE", "IT", "LV", "LT", "LU", "MY", "MT", "MX", "NL", "NZ", "NI", "NO", "PA", "PY", "PE", "PH", "PL", "PT", "SG", "SK", "ES", "SE", "CH", "TW", "TR", "UY", "US", "GB", "AD", "LI", "MC", "ID", "JP", "TH", "VN", "RO", "IL", "ZA", "SA", "AE", "BH", "QA", "OM", "KW", "EG", "MA", "DZ", "TN", "LB", "JO", "PS", "IN", "BY", "KZ", "MD", "UA", "AL", "BA", "HR", "ME", "MK", "RS", "SI", "KR", "BD", "PK", "LK", "GH", "KE", "NG", "TZ", "UG", "AG", "AM", "BS", "BB", "BZ", "BT", "BW", "BF", "CV", "CW", "DM", "FJ", "GM", "GE", "GD", "GW", "GY", "HT", "JM", "KI", "LS", "LR", "MW", "MV", "ML", "MH", "FM", "NA", "NR", "NE", "PW", "PG", "WS", "SM", "ST", "SN", "SC", "SL", "SB", "KN", "LC", "VC", "SR", "TL", "TO", "TT", "TV", "VU", "AZ", "BN", "BI", "KH", "CM", "TD", "KM", "GQ", "SZ", "GA", "GN", "KG", "LA", "MO", "MR", "MN", "NP", "RW", "TG", "UZ", "ZW", "BJ", "MG", "MU", "MZ", "AO", "CI", "DJ", "ZM", "CD", "CG", "IQ", "LY", "TJ", "VE", "ET", "XK"], "external_urls": {"spotify": "https://open.spotify.com/album/6dZ385OGfbTj1EYMidKTH8"}, "href": "https://api.spotify.com/v1/albums/6dZ385OGfbTj1EYMidKTH8", "id": "6dZ385OGfbTj1EYMidKTH8", "images": [{"height": 640, "url": "https://i.scdn.co/image/ab67616d0000b27390ae8b6fa9574f3ae0fc992d", "width": 640}, {"height": 300, "url": "https://i.scdn.co/image/ab67616d00001e0290ae8b6fa9574f3ae0fc992d", "width": 300}, {"height": 64, "url": "https://i.scdn.co/image/ab67616d0000485190ae8b6fa9574f3ae0fc992d", "width": 64}], "name": "Alev Alev", "release_date": "2019-10-25", "release_date_precision": "day", "total_tracks": 1, "type": "album", "uri": "spotify:album:6dZ385OGfbTj1EYMidKTH8"}, {"album_group": "single", "album_type": "single", "artists": [{"external_urls": {"spotify": "https://open.spotify.com/artist/0Qbd0AGWuzggX61s306wZN"}, "href": "https://api.spotify.com/v1/artists/0Qbd0AGWuzggX61s306wZN", "id": "0Qbd0AGWuzggX61s306wZN", "name": "Ebru Ya\u015far", "type": "artist", "uri": "spotify:artist:0Qbd0AGWuzggX61s306wZN"}], "available_markets": ["AR", "AU", "AT", "BE", "BO", "BR", "BG", "CA", "CL", "CO", "CR", "CY", "CZ", "DK", "DO", "DE", "EC", "EE", "SV", "FI", "FR", "GR", "GT", "HN", "HK", "HU", "IS", "IE", "IT", "LV", "LT", "LU", "MY", "MT", "MX", "NL", "NZ", "NI", "NO", "PA", "PY", "PE", "PH", "PL", "PT", "SG", "SK", "ES", "SE", "CH", "TW", "TR", "UY", "US", "GB", "AD", "LI", "MC", "ID", "JP", "TH", "VN", "RO", "IL", "ZA", "SA", "AE", "BH", "QA", "OM", "KW", "EG", "MA", "DZ", "TN", "LB", "JO", "PS", "IN", "BY", "KZ", "MD", "UA", "AL", "BA", "HR", "ME", "MK", "RS", "SI", "KR", "BD", "PK", "LK", "GH", "KE", "NG", "TZ", "UG", "AG", "AM", "BS", "BB", "BZ", "BT", "BW", "BF", "CV", "CW", "DM", "FJ", "GM", "GE", "GD", "GW", "GY", "HT", "JM", "KI", "LS", "LR", "MW", "MV", "ML", "MH", "FM", "NA", "NR", "NE", "PW", "PG", "WS", "SM", "ST", "SN", "SC", "SL", "SB", "KN", "LC", "VC", "SR", "TL", "TO", "TT", "TV", "VU", "AZ", "BN", "BI", "KH", "CM", "TD", "KM", "GQ", "SZ", "GA", "GN", "KG", "LA", "MO", "MR", "MN", "NP", "RW", "TG", "UZ", "ZW", "BJ", "MG", "MU", "MZ", "AO", "CI", "DJ", "ZM", "CD", "CG", "IQ", "LY", "TJ", "VE", "ET", "XK"], "external_urls": {"spotify": "https://open.spotify.com/album/1OR22R9h2rNP4fFp0JHT1N"}, "href": "https://api.spotify.com/v1/albums/1OR22R9h2rNP4fFp0JHT1N", "id": "1OR22R9h2rNP4fFp0JHT1N", "images": [{"height": 640, "url": "https://i.scdn.co/image/ab67616d0000b273ec16dfd2b8e8f521784f75c0", "width": 640}, {"height": 300, "url": "https://i.scdn.co/image/ab67616d00001e02ec16dfd2b8e8f521784f75c0", "width": 300}, {"height": 64, "url": "https://i.scdn.co/image/ab67616d00004851ec16dfd2b8e8f521784f75c0", "width": 64}], "name": "Cumartesi", "release_date": "2014-12-02", "release_date_precision": "day", "total_tracks": 1, "type": "album", "uri": "spotify:album:1OR22R9h2rNP4fFp0JHT1N"}, {"album_group": "single", "album_type": "single", "artists": [{"external_urls": {"spotify": "https://open.spotify.com/artist/0Qbd0AGWuzggX61s306wZN"}, "href": "https://api.spotify.com/v1/artists/0Qbd0AGWuzggX61s306wZN", "id": "0Qbd0AGWuzggX61s306wZN", "name": "Ebru Ya\u015far", "type": "artist", "uri": "spotify:artist:0Qbd0AGWuzggX61s306wZN"}], "available_markets": ["AR", "AU", "AT", "BE", "BO", "BR", "BG", "CA", "CL", "CO", "CR", "CY", "CZ", "DK", "DO", "DE", "EC", "EE", "SV", "FI", "FR", "GR", "GT", "HN", "HK", "HU", "IS", "IE", "IT", "LV", "LT", "LU", "MY", "MT", "MX", "NL", "NZ", "NI", "NO", "PA", "PY", "PE", "PH", "PL", "PT", "SG", "SK", "ES", "SE", "CH", "TW", "TR", "UY", "US", "GB", "AD", "LI", "MC", "ID", "JP", "TH", "VN", "RO", "IL", "ZA", "SA", "AE", "BH", "QA", "OM", "KW", "EG", "MA", "DZ", "TN", "LB", "JO", "PS", "IN", "BY", "KZ", "MD", "UA", "AL", "BA", "HR", "ME", "MK", "RS", "SI", "KR", "BD", "PK", "LK", "GH", "KE", "NG", "TZ", "UG", "AG", "AM", "BS", "BB", "BZ", "BT", "BW", "BF", "CV", "CW", "DM", "FJ", "GM", "GE", "GD", "GW", "GY", "HT", "JM", "KI", "LS", "LR", "MW", "MV", "ML", "MH", "FM", "NA", "NR", "NE", "PW", "PG", "WS", "SM", "ST", "SN", "SC", "SL", "SB", "KN", "LC", "VC", "SR", "TL", "TO", "TT", "TV", "VU", "AZ", "BN", "BI", "KH", "CM", "TD", "KM", "GQ", "SZ", "GA", "GN", "KG", "LA", "MO", "MR", "MN", "NP", "RW", "TG", "UZ", "ZW", "BJ", "MG", "MU", "MZ", "AO", "CI", "DJ", "ZM", "CD", "CG", "IQ", "LY", "TJ", "VE", "ET", "XK"], "external_urls": {"spotify": "https://open.spotify.com/album/0tdSmk1sRtScCpnxFOW1Ie"}, "href": "https://api.spotify.com/v1/albums/0tdSmk1sRtScCpnxFOW1Ie", "id": "0tdSmk1sRtScCpnxFOW1Ie", "images": [{"height": 640, "url": "https://i.scdn.co/image/ab67616d0000b273f6e2110c71455ad6a9a90961", "width": 640}, {"height": 300, "url": "https://i.scdn.co/image/ab67616d00001e02f6e2110c71455ad6a9a90961", "width": 300}, {"height": 64, "url": "https://i.scdn.co/image/ab67616d00004851f6e2110c71455ad6a9a90961", "width": 64}], "name": "A\u011flayam\u0131yorum", "release_date": "2012-06-19", "release_date_precision": "day", "total_tracks": 1, "type": "album", "uri": "spotify:album:0tdSmk1sRtScCpnxFOW1Ie"}, {"album_group": "appears_on", "album_type": "album", "artists": [{"external_urls": {"spotify": "https://open.spotify.com/artist/7FvMAbdiffitFmbuJN3Vsk"}, "href": "https://api.spotify.com/v1/artists/7FvMAbdiffitFmbuJN3Vsk", "id": "7FvMAbdiffitFmbuJN3Vsk", "name": "Emrah Karaduman", "type": "artist", "uri": "spotify:artist:7FvMAbdiffitFmbuJN3Vsk"}], "available_markets": ["AR", "AU", "AT", "BE", "BO", "BR", "BG", "CA", "CL", "CO", "CR", "CY", "CZ", "DK", "DO", "DE", "EC", "EE", "SV", "FI", "FR", "GR", "GT", "HN", "HK", "HU", "IS", "IE", "IT", "LV", "LT", "LU", "MY", "MT", "MX", "NL", "NZ", "NI", "NO", "PA", "PY", "PE", "PH", "PL", "PT", "SG", "SK", "ES", "SE", "CH", "TW", "TR", "UY", "US", "GB", "AD", "LI", "MC", "ID", "JP", "TH", "VN", "RO", "IL", "ZA", "SA", "AE", "BH", "QA", "OM", "KW", "EG", "MA", "DZ", "TN", "LB", "JO", "PS", "IN", "BY", "KZ", "MD", "UA", "AL", "BA", "HR", "ME", "MK", "RS", "SI", "KR", "BD", "PK", "LK", "GH", "KE", "NG", "TZ", "UG", "AG", "AM", "BS", "BB", "BZ", "BT", "BW", "BF", "CV", "CW", "DM", "FJ", "GM", "GE", "GD", "GW", "GY", "HT", "JM", "KI", "LS", "LR", "MW", "MV", "ML", "MH", "FM", "NA", "NR", "NE", "PW", "PG", "WS", "SM", "ST", "SN", "SC", "SL", "SB", "KN", "LC", "VC", "SR", "TL", "TO", "TT", "TV", "VU", "AZ", "BN", "BI", "KH", "CM", "TD", "KM", "GQ", "SZ", "GA", "GN", "KG", "LA", "MO", "MR", "MN", "NP", "RW", "TG", "UZ", "ZW", "BJ", "MG", "MU", "MZ", "AO", "CI", "DJ", "ZM", "CD", "CG", "IQ", "LY", "TJ", "VE", "ET", "XK"], "external_urls": {"spotify": "https://open.spotify.com/album/1QWwjp3eDSg0OGlo4J0MY9"}, "href": "https://api.spotify.com/v1/albums/1QWwjp3eDSg0OGlo4J0MY9", "id": "1QWwjp3eDSg0OGlo4J0MY9", "images": [{"height": 640, "url": "https://i.scdn.co/image/ab67616d0000b273db7e1c0da9c1023dc30f3e14", "width": 640}, {"height": 300, "url": "https://i.scdn.co/image/ab67616d00001e02db7e1c0da9c1023dc30f3e14", "width": 300}, {"height": 64, "url": "https://i.scdn.co/image/ab67616d00004851db7e1c0da9c1023dc30f3e14", "width": 64}], "name": "BombarDuman", "release_date": "2018-09-17", "release_date_precision": "day", "total_tracks": 9, "type": "album", "uri": "spotify:album:1QWwjp3eDSg0OGlo4J0MY9"}, {"album_group": "appears_on", "album_type": "compilation", "artists": [{"external_urls": {"spotify": "https://open.spotify.com/artist/0LyfQWJT6nXafLPZqxe9Of"}, "href": "https://api.spotify.com/v1/artists/0LyfQWJT6nXafLPZqxe9Of", "id": "0LyfQWJT6nXafLPZqxe9Of", "name": "Various Artists", "type": "artist", "uri": "spotify:artist:0LyfQWJT6nXafLPZqxe9Of"}], "available_markets": ["AR", "AU", "AT", "BE", "BO", "BR", "BG", "CA", "CL", "CO", "CR", "CY", "CZ", "DK", "DO", "DE", "EC", "EE", "SV", "FI", "FR", "GR", "GT", "HN", "HK", "HU", "IS", "IE", "IT", "LV", "LT", "LU", "MY", "MT", "MX", "NL", "NZ", "NI", "NO", "PA", "PY", "PE", "PH", "PL", "PT", "SG", "SK", "ES", "SE", "CH", "TW", "TR", "UY", "US", "GB", "AD", "LI", "MC", "ID", "JP", "TH", "VN", "RO", "IL", "ZA", "SA", "AE", "BH", "QA", "OM", "KW", "EG", "MA", "DZ", "TN", "LB", "JO", "PS", "IN", "BY", "KZ", "MD", "UA", "AL", "BA", "HR", "ME", "MK", "RS", "SI", "KR", "BD", "PK", "LK", "GH", "KE", "NG", "TZ", "UG", "AG", "AM", "BS", "BB", "BZ", "BT", "BW", "BF", "CV", "CW", "DM", "FJ", "GM", "GE", "GD", "GW", "GY", "HT", "JM", "KI", "LS", "LR", "MW", "MV", "ML", "MH", "FM", "NA", "NR", "NE", "PW", "PG", "WS", "SM", "ST", "SN", "SC", "SL", "SB", "KN", "LC", "VC", "SR", "TL", "TO", "TT", "TV", "VU", "AZ", "BN", "BI", "KH", "CM", "TD", "KM", "GQ", "SZ", "GA", "GN", "KG", "LA", "MO", "MR", "MN", "NP", "RW", "TG", "UZ", "ZW", "BJ", "MG", "MU", "MZ", "AO", "CI", "DJ", "ZM", "CD", "CG", "IQ", "LY", "TJ", "VE", "ET", "XK"], "external_urls": {"spotify": "https://open.spotify.com/album/31Ldcd5NsHMPg6wIyg5d7a"}, "href": "https://api.spotify.com/v1/albums/31Ldcd5NsHMPg6wIyg5d7a", "id": "31Ldcd5NsHMPg6wIyg5d7a", "images": [{"height": 640, "url": "https://i.scdn.co/image/ab67616d0000b273c0ec3a0f1196e1f5a043009c", "width": 640}, {"height": 300, "url": "https://i.scdn.co/image/ab67616d00001e02c0ec3a0f1196e1f5a043009c", "width": 300}, {"height": 64, "url": "https://i.scdn.co/image/ab67616d00004851c0ec3a0f1196e1f5a043009c", "width": 64}], "name": "Ahmet Sel\u00e7uk \u0130lkan Unutulmayan \u015eark\u0131lar, Vol. 4", "release_date": "2018-12-19", "release_date_precision": "day", "total_tracks": 17, "type": "album", "uri": "spotify:album:31Ldcd5NsHMPg6wIyg5d7a"}, {"album_group": "appears_on", "album_type": "compilation", "artists": [{"external_urls": {"spotify": "https://open.spotify.com/artist/0LyfQWJT6nXafLPZqxe9Of"}, "href": "https://api.spotify.com/v1/artists/0LyfQWJT6nXafLPZqxe9Of", "id": "0LyfQWJT6nXafLPZqxe9Of", "name": "Various Artists", "type": "artist", "uri": "spotify:artist:0LyfQWJT6nXafLPZqxe9Of"}], "available_markets": ["AR", "AU", "AT", "BE", "BO", "BR", "BG", "CA", "CL", "CO", "CR", "CY", "CZ", "DK", "DO", "DE", "EC", "EE", "SV", "FI", "FR", "GR", "GT", "HN", "HK", "HU", "IS", "IE", "IT", "LV", "LT", "LU", "MY", "MT", "MX", "NL", "NZ", "NI", "NO", "PA", "PY", "PE", "PH", "PL", "PT", "SG", "SK", "ES", "SE", "CH", "TW", "TR", "UY", "US", "GB", "AD", "LI", "MC", "ID", "JP", "TH", "VN", "RO", "IL", "ZA", "SA", "AE", "BH", "QA", "OM", "KW", "EG", "MA", "DZ", "TN", "LB", "JO", "PS", "IN", "BY", "KZ", "MD", "UA", "AL", "BA", "HR", "ME", "MK", "RS", "SI", "KR", "BD", "PK", "LK", "GH", "KE", "NG", "TZ", "UG", "AG", "AM", "BS", "BB", "BZ", "BT", "BW", "BF", "CV", "CW", "DM", "FJ", "GM", "GE", "GD", "GW", "GY", "HT", "JM", "KI", "LS", "LR", "MW", "MV", "ML", "MH", "FM", "NA", "NR", "NE", "PW", "PG", "WS", "SM", "ST", "SN", "SC", "SL", "SB", "KN", "LC", "VC", "SR", "TL", "TO", "TT", "TV", "VU", "AZ", "BN", "BI", "KH", "CM", "TD", "KM", "GQ", "SZ", "GA", "GN", "KG", "LA", "MO", "MR", "MN", "NP", "RW", "TG", "UZ", "ZW", "BJ", "MG", "MU", "MZ", "AO", "CI", "DJ", "ZM", "CD", "CG", "IQ", "LY", "TJ", "VE", "ET", "XK"], "external_urls": {"spotify": "https://open.spotify.com/album/6nMHzx1r5oYgaiGO0GEp6n"}, "href": "https://api.spotify.com/v1/albums/6nMHzx1r5oYgaiGO0GEp6n", "id": "6nMHzx1r5oYgaiGO0GEp6n", "images": [{"height": 640, "url": "https://i.scdn.co/image/ab67616d0000b273b3d371854bc5e4a72eb65d74", "width": 640}, {"height": 300, "url": "https://i.scdn.co/image/ab67616d00001e02b3d371854bc5e4a72eb65d74", "width": 300}, {"height": 64, "url": "https://i.scdn.co/image/ab67616d00004851b3d371854bc5e4a72eb65d74", "width": 64}], "name": "Ahmet Sel\u00e7uk \u0130lkan Unutulmayan \u015eark\u0131lar, Vol. 3", "release_date": "2018-12-19", "release_date_precision": "day", "total_tracks": 17, "type": "album", "uri": "spotify:album:6nMHzx1r5oYgaiGO0GEp6n"}, {"album_group": "appears_on", "album_type": "album", "artists": [{"external_urls": {"spotify": "https://open.spotify.com/artist/1oQWUhY5ph2NKxrdsTPiHk"}, "href": "https://api.spotify.com/v1/artists/1oQWUhY5ph2NKxrdsTPiHk", "id": "1oQWUhY5ph2NKxrdsTPiHk", "name": "Ahmet Sel\u00e7uk \u0130lkan", "type": "artist", "uri": "spotify:artist:1oQWUhY5ph2NKxrdsTPiHk"}], "available_markets": ["AR", "AU", "AT", "BE", "BO", "BR", "BG", "CA", "CL", "CO", "CR", "CY", "CZ", "DK", "DO", "DE", "EC", "EE", "SV", "FI", "FR", "GR", "GT", "HN", "HK", "HU", "IS", "IE", "IT", "LV", "LT", "LU", "MY", "MT", "MX", "NL", "NZ", "NI", "NO", "PA", "PY", "PE", "PH", "PL", "PT", "SG", "SK", "ES", "SE", "CH", "TW", "TR", "UY", "US", "GB", "AD", "LI", "MC", "ID", "JP", "TH", "VN", "RO", "IL", "ZA", "SA", "AE", "BH", "QA", "OM", "KW", "EG", "MA", "DZ", "TN", "LB", "JO", "PS", "IN", "BY", "KZ", "MD", "UA", "AL", "BA", "HR", "ME", "MK", "RS", "SI", "KR", "BD", "PK", "LK", "GH", "KE", "NG", "TZ", "UG", "AG", "AM", "BS", "BB", "BZ", "BT", "BW", "BF", "CV", "CW", "DM", "FJ", "GM", "GE", "GD", "GW", "GY", "HT", "JM", "KI", "LS", "LR", "MW", "MV", "ML", "MH", "FM", "NA", "NR", "NE", "PW", "PG", "WS", "SM", "ST", "SN", "SC", "SL", "SB", "KN", "LC", "VC", "SR", "TL", "TO", "TT", "TV", "VU", "AZ", "BN", "BI", "KH", "CM", "TD", "KM", "GQ", "SZ", "GA", "GN", "KG", "LA", "MO", "MR", "MN", "NP", "RW", "TG", "UZ", "ZW", "BJ", "MG", "MU", "MZ", "AO", "CI", "DJ", "ZM", "CD", "CG", "IQ", "LY", "TJ", "VE", "ET", "XK"], "external_urls": {"spotify": "https://open.spotify.com/album/6w86rXw9DJENnA81cc19kM"}, "href": "https://api.spotify.com/v1/albums/6w86rXw9DJENnA81cc19kM", "id": "6w86rXw9DJENnA81cc19kM", "images": [{"height": 640, "url": "https://i.scdn.co/image/ab67616d0000b27318de702cba466030273a3465", "width": 640}, {"height": 300, "url": "https://i.scdn.co/image/ab67616d00001e0218de702cba466030273a3465", "width": 300}, {"height": 64, "url": "https://i.scdn.co/image/ab67616d0000485118de702cba466030273a3465", "width": 64}], "name": "S\u00f6z", "release_date": "2020-04-21", "release_date_precision": "day", "total_tracks": 14, "type": "album", "uri": "spotify:album:6w86rXw9DJENnA81cc19kM"}, {"album_group": "appears_on", "album_type": "compilation", "artists": [{"external_urls": {"spotify": "https://open.spotify.com/artist/0LyfQWJT6nXafLPZqxe9Of"}, "href": "https://api.spotify.com/v1/artists/0LyfQWJT6nXafLPZqxe9Of", "id": "0LyfQWJT6nXafLPZqxe9Of", "name": "Various Artists", "type": "artist", "uri": "spotify:artist:0LyfQWJT6nXafLPZqxe9Of"}], "available_markets": ["AR", "AU", "AT", "BE", "BO", "BR", "BG", "CA", "CL", "CO", "CR", "CY", "CZ", "DK", "DO", "DE", "EC", "EE", "SV", "FI", "FR", "GR", "GT", "HN", "HK", "HU", "IS", "IE", "IT", "LV", "LT", "LU", "MY", "MT", "MX", "NL", "NZ", "NI", "NO", "PA", "PY", "PE", "PH", "PL", "PT", "SG", "SK", "ES", "SE", "CH", "TW", "TR", "UY", "US", "GB", "AD", "LI", "MC", "ID", "JP", "TH", "VN", "RO", "IL", "ZA", "SA", "AE", "BH", "QA", "OM", "KW", "EG", "MA", "DZ", "TN", "LB", "JO", "PS", "IN", "BY", "KZ", "MD", "UA", "AL", "BA", "HR", "ME", "MK", "RS", "SI", "KR", "BD", "PK", "LK", "GH", "KE", "NG", "TZ", "UG", "AG", "AM", "BS", "BB", "BZ", "BT", "BW", "BF", "CV", "CW", "DM", "FJ", "GM", "GE", "GD", "GW", "GY", "HT", "JM", "KI", "LS", "LR", "MW", "MV", "ML", "MH", "FM", "NA", "NR", "NE", "PW", "PG", "WS", "SM", "ST", "SN", "SC", "SL", "SB", "KN", "LC", "VC", "SR", "TL", "TO", "TT", "TV", "VU", "AZ", "BN", "BI", "KH", "CM", "TD", "KM", "GQ", "SZ", "GA", "GN", "KG", "LA", "MO", "MR", "MN", "NP", "RW", "TG", "UZ", "ZW", "BJ", "MG", "MU", "MZ", "AO", "CI", "DJ", "ZM", "CD", "CG", "IQ", "LY", "TJ", "VE", "ET", "XK"], "external_urls": {"spotify": "https://open.spotify.com/album/6YJUOeIOdVdMIzGco9FpG4"}, "href": "https://api.spotify.com/v1/albums/6YJUOeIOdVdMIzGco9FpG4", "id": "6YJUOeIOdVdMIzGco9FpG4", "images": [{"height": 640, "url": "https://i.scdn.co/image/ab67616d0000b273cde7b89ed8fe9ced5670a7da", "width": 640}, {"height": 300, "url": "https://i.scdn.co/image/ab67616d00001e02cde7b89ed8fe9ced5670a7da", "width": 300}, {"height": 64, "url": "https://i.scdn.co/image/ab67616d00004851cde7b89ed8fe9ced5670a7da", "width": 64}], "name": "45 Y\u0131ll\u0131k Baba \u015eark\u0131lar (50 Sanat\u00e7\u0131 - 48 Eser)", "release_date": "2013-11-12", "release_date_precision": "day", "total_tracks": 48, "type": "album", "uri": "spotify:album:6YJUOeIOdVdMIzGco9FpG4"}, {"album_group": "appears_on", "album_type": "compilation", "artists": [{"external_urls": {"spotify": "https://open.spotify.com/artist/0LyfQWJT6nXafLPZqxe9Of"}, "href": "https://api.spotify.com/v1/artists/0LyfQWJT6nXafLPZqxe9Of", "id": "0LyfQWJT6nXafLPZqxe9Of", "name": "Various Artists", "type": "artist", "uri": "spotify:artist:0LyfQWJT6nXafLPZqxe9Of"}], "available_markets": ["AR", "AU", "AT", "BE", "BO", "BR", "BG", "CA", "CL", "CO", "CR", "CY", "CZ", "DK", "DO", "DE", "EC", "EE", "SV", "FI", "FR", "GR", "GT", "HN", "HK", "HU", "IS", "IE", "IT", "LV", "LT", "LU", "MY", "MT", "MX", "NL", "NZ", "NI", "NO", "PA", "PY", "PE", "PH", "PL", "PT", "SG", "SK", "ES", "SE", "CH", "TW", "TR", "UY", "US", "GB", "AD", "LI", "MC", "ID", "JP", "TH", "VN", "RO", "IL", "ZA", "SA", "AE", "BH", "QA", "OM", "KW", "EG", "MA", "DZ", "TN", "LB", "JO", "PS", "IN", "BY", "KZ", "MD", "UA", "AL", "BA", "HR", "ME", "MK", "RS", "SI", "KR", "BD", "PK", "LK", "GH", "KE", "NG", "TZ", "UG", "AG", "AM", "BS", "BB", "BZ", "BT", "BW", "BF", "CV", "CW", "DM", "FJ", "GM", "GE", "GD", "GW", "GY", "HT", "JM", "KI", "LS", "LR", "MW", "MV", "ML", "MH", "FM", "NA", "NR", "NE", "PW", "PG", "WS", "SM", "ST", "SN", "SC", "SL", "SB", "KN", "LC", "VC", "SR", "TL", "TO", "TT", "TV", "VU", "AZ", "BN", "BI", "KH", "CM", "TD", "KM", "GQ", "SZ", "GA", "GN", "KG", "LA", "MO", "MR", "MN", "NP", "RW", "TG", "UZ", "ZW", "BJ", "MG", "MU", "MZ", "AO", "CI", "DJ", "ZM", "CD", "CG", "IQ", "LY", "TJ", "VE", "ET", "XK"], "external_urls": {"spotify": "https://open.spotify.com/album/5Wh90UbKrvvhISDOIMoqOH"}, "href": "https://api.spotify.com/v1/albums/5Wh90UbKrvvhISDOIMoqOH", "id": "5Wh90UbKrvvhISDOIMoqOH", "images": [{"height": 640, "url": "https://i.scdn.co/image/ab67616d0000b27316f99e7106190bf777bf9edf", "width": 640}, {"height": 300, "url": "https://i.scdn.co/image/ab67616d00001e0216f99e7106190bf777bf9edf", "width": 300}, {"height": 64, "url": "https://i.scdn.co/image/ab67616d0000485116f99e7106190bf777bf9edf", "width": 64}], "name": "Baba \u015eark\u0131lar, Vol.2", "release_date": "2013-01-21", "release_date_precision": "day", "total_tracks": 27, "type": "album", "uri": "spotify:album:5Wh90UbKrvvhISDOIMoqOH"}, {"album_group": "appears_on", "album_type": "compilation", "artists": [{"external_urls": {"spotify": "https://open.spotify.com/artist/0LyfQWJT6nXafLPZqxe9Of"}, "href": "https://api.spotify.com/v1/artists/0LyfQWJT6nXafLPZqxe9Of", "id": "0LyfQWJT6nXafLPZqxe9Of", "name": "Various Artists", "type": "artist", "uri": "spotify:artist:0LyfQWJT6nXafLPZqxe9Of"}], "available_markets": ["AR", "AU", "AT", "BE", "BO", "BR", "BG", "CA", "CL", "CO", "CR", "CY", "CZ", "DK", "DO", "DE", "EC", "EE", "SV", "FI", "FR", "GR", "GT", "HN", "HK", "HU", "IS", "IE", "IT", "LV", "LT", "LU", "MY", "MT", "MX", "NL", "NZ", "NI", "NO", "PA", "PY", "PE", "PH", "PL", "PT", "SG", "SK", "ES", "SE", "CH", "TW", "TR", "UY", "US", "GB", "AD", "LI", "MC", "ID", "JP", "TH", "VN", "RO", "IL", "ZA", "SA", "AE", "BH", "QA", "OM", "KW", "EG", "MA", "DZ", "TN", "LB", "JO", "PS", "IN", "BY", "KZ", "MD", "UA", "AL", "BA", "HR", "ME", "MK", "RS", "SI", "KR", "BD", "PK", "LK", "GH", "KE", "NG", "TZ", "UG", "AG", "AM", "BS", "BB", "BZ", "BT", "BW", "BF", "CV", "CW", "DM", "FJ", "GM", "GE", "GD", "GW", "GY", "HT", "JM", "KI", "LS", "LR", "MW", "MV", "ML", "MH", "FM", "NA", "NR", "NE", "PW", "PG", "WS", "SM", "ST", "SN", "SC", "SL", "SB", "KN", "LC", "VC", "SR", "TL", "TO", "TT", "TV", "VU", "AZ", "BN", "BI", "KH", "CM", "TD", "KM", "GQ", "SZ", "GA", "GN", "KG", "LA", "MO", "MR", "MN", "NP", "RW", "TG", "UZ", "ZW", "BJ", "MG", "MU", "MZ", "AO", "CI", "DJ", "ZM", "CD", "CG", "IQ", "LY", "TJ", "VE", "ET", "XK"], "external_urls": {"spotify": "https://open.spotify.com/album/4oXXXf5udQQWQfsQGBm7yC"}, "href": "https://api.spotify.com/v1/albums/4oXXXf5udQQWQfsQGBm7yC", "id": "4oXXXf5udQQWQfsQGBm7yC", "images": [{"height": 640, "url": "https://i.scdn.co/image/ab67616d0000b273dc393bb63e649e378b27659d", "width": 640}, {"height": 300, "url": "https://i.scdn.co/image/ab67616d00001e02dc393bb63e649e378b27659d", "width": 300}, {"height": 64, "url": "https://i.scdn.co/image/ab67616d00004851dc393bb63e649e378b27659d", "width": 64}], "name": "G\u00fc\u00e7l\u00fc Kad\u0131nlar G\u00fc\u00e7l\u00fc \u015eark\u0131lar", "release_date": "2019-03-08", "release_date_precision": "day", "total_tracks": 18, "type": "album", "uri": "spotify:album:4oXXXf5udQQWQfsQGBm7yC"}, {"album_group": "appears_on", "album_type": "compilation", "artists": [{"external_urls": {"spotify": "https://open.spotify.com/artist/0LyfQWJT6nXafLPZqxe9Of"}, "href": "https://api.spotify.com/v1/artists/0LyfQWJT6nXafLPZqxe9Of", "id": "0LyfQWJT6nXafLPZqxe9Of", "name": "Various Artists", "type": "artist", "uri": "spotify:artist:0LyfQWJT6nXafLPZqxe9Of"}], "available_markets": ["AR", "AU", "AT", "BE", "BO", "BR", "BG", "CA", "CL", "CO", "CR", "CY", "CZ", "DK", "DO", "DE", "EC", "EE", "SV", "FI", "FR", "GR", "GT", "HN", "HK", "HU", "IS", "IE", "IT", "LV", "LT", "LU", "MY", "MT", "MX", "NL", "NZ", "NI", "NO", "PA", "PY", "PE", "PH", "PL", "PT", "SG", "SK", "ES", "SE", "CH", "TW", "TR", "UY", "US", "GB", "AD", "LI", "MC", "ID", "JP", "TH", "VN", "RO", "IL", "ZA", "SA", "AE", "BH", "QA", "OM", "KW", "EG", "MA", "DZ", "TN", "LB", "JO", "PS", "IN", "BY", "KZ", "MD", "UA", "AL", "BA", "HR", "ME", "MK", "RS", "SI", "KR", "BD", "PK", "LK", "GH", "KE", "NG", "TZ", "UG", "AG", "AM", "BS", "BB", "BZ", "BT", "BW", "BF", "CV", "CW", "DM", "FJ", "GM", "GE", "GD", "GW", "GY", "HT", "JM", "KI", "LS", "LR", "MW", "MV", "ML", "MH", "FM", "NA", "NR", "NE", "PW", "PG", "WS", "SM", "ST", "SN", "SC", "SL", "SB", "KN", "LC", "VC", "SR", "TL", "TO", "TT", "TV", "VU", "AZ", "BN", "BI", "KH", "CM", "TD", "KM", "GQ", "SZ", "GA", "GN", "KG", "LA", "MO", "MR", "MN", "NP", "RW", "TG", "UZ", "ZW", "BJ", "MG", "MU", "MZ", "AO", "CI", "DJ", "ZM", "CD", "CG", "IQ", "LY", "TJ", "VE", "ET", "XK"], "external_urls": {"spotify": "https://open.spotify.com/album/4yvYmKvdKfKRZASaUZkvsa"}, "href": "https://api.spotify.com/v1/albums/4yvYmKvdKfKRZASaUZkvsa", "id": "4yvYmKvdKfKRZASaUZkvsa", "images": [{"height": 640, "url": "https://i.scdn.co/image/ab67616d0000b27377e1801369f1af725874ca67", "width": 640}, {"height": 300, "url": "https://i.scdn.co/image/ab67616d00001e0277e1801369f1af725874ca67", "width": 300}, {"height": 64, "url": "https://i.scdn.co/image/ab67616d0000485177e1801369f1af725874ca67", "width": 64}], "name": "Fantezi \u015eark\u0131lar Y\u0131ld\u0131zlar Ge\u00e7idi, Vol. 1", "release_date": "2014-02-12", "release_date_precision": "day", "total_tracks": 20, "type": "album", "uri": "spotify:album:4yvYmKvdKfKRZASaUZkvsa"}]